tgmount/__init__.py
tgmount/client.py
tgmount/error.py
tgmount/settings.py
tgmount/tglog.py
tgmount/util.py
tgmount/cache/__init__.py
tgmount/cache/cache_in_blocks.py
tgmount/cache/file.py
tgmount/cache/file_source.py
tgmount/cache/logger.py
tgmount/cache/memory.py
tgmount/cache/reader.py
tgmount/cache/types.py
tgmount/cache/util.py
tgmount/cli/__init__.py
tgmount/cli/auth.py
tgmount/cli/download.py
tgmount/cli/list_dialogs.py
tgmount/cli/list_documents.py
tgmount/cli/logger.py
tgmount/cli/mount.py
tgmount/cli/mount_config.py
tgmount/cli/stats.py
tgmount/cli/validate.py
tgmount/cli/util/__init__.py
tgmount/cli/util/client.py
tgmount/cli/util/config.py
tgmount/cli/util/read_env.py
tgmount/common/__init__.py
tgmount/common/filter.py
tgmount/config/__init__.py
tgmount/config/config.py
tgmount/config/config_type.py
tgmount/config/error.py
tgmount/config/helpers.py
tgmount/config/logger.py
tgmount/config/reader.py
tgmount/config/types.py
tgmount/config/util.py
tgmount/controlserver/__init__.py
tgmount/controlserver/server.py
tgmount/fs/__init__.py
tgmount/fs/fh.py
tgmount/fs/inode.py
tgmount/fs/logger.py
tgmount/fs/operations.py
tgmount/fs/update.py
tgmount/fs/util.py
tgmount/main/__init__.py
tgmount/main/util.py
tgmount/tgclient/__init__.py
tgmount/tgclient/auth.py
tgmount/tgclient/client.py
tgmount/tgclient/client_types.py
tgmount/tgclient/events_disptacher.py
tgmount/tgclient/fetcher.py
tgmount/tgclient/files_source.py
tgmount/tgclient/filters.py
tgmount/tgclient/guards.py
tgmount/tgclient/logger.py
tgmount/tgclient/message_reaction_event.py
tgmount/tgclient/message_source.py
tgmount/tgclient/message_source_types.py
tgmount/tgclient/message_types.py
tgmount/tgclient/messages_collection.py
tgmount/tgclient/types.py
tgmount/tgclient/util.py
tgmount/tgclient/search/__init__.py
tgmount/tgclient/search/search.py
tgmount/tgclient/search/types.py
tgmount/tgclient/search/util.py
tgmount/tgclient/source/__init__.py
tgmount/tgclient/source/base.py
tgmount-1.0.2.dist-info/METADATA
tgmount-1.0.2.dist-info/WHEEL
tgmount-1.0.2.dist-info/entry_points.txt
tgmount-1.0.2.dist-info/top_level.txt
tgmount-1.0.2.dist-info/RECORD
