Metadata-Version: 2.1
Name: tgmount
Version: 1.0.2
Summary: Mount telegram messages as files
Home-page: https://github.com/nktknshn/tgmount-ng
Author: Nikita Kanashin
Author-email: nikita@kanash.in
Requires-Dist: telethon
Requires-Dist: typing-extensions
Requires-Dist: greenback
Requires-Dist: aiofiles
Requires-Dist: pyyaml
Requires-Dist: tqdm
Requires-Dist: pyfuse3
